{
  "hash": "138dd48b4064",
  "n_appearances": 2,
  "n_distinct_urls": 1,
  "sources": [
    {
      "url": "https://br.reuters.com/business/energy/oil-jumps-10-iran-conflict-could-spike-100-barrel-analysts-say-2026-03-01/",
      "title": "Reuters | Breaking International News & Views",
      "published_date": "2026-03-01T00:00:00.000Z",
      "author": null,
      "num_tokens": 28,
      "text_length": 148
    }
  ],
  "appearances": [
    {
      "market_id": "1467763",
      "spike_id": 1,
      "market_question": "Will Crude Oil (CL) hit (HIGH) $120 by end of March?",
      "event_title": "Will Crude Oil (CL) hit__ by end of March?",
      "spike_direction": "down",
      "spike_delta": -0.42,
      "spike_timestamp_before": "2026-02-28T19:30:32+00:00",
      "spike_timestamp_after": "2026-02-28T21:00:35+00:00"
    },
    {
      "market_id": "1467765",
      "spike_id": 1,
      "market_question": "Will Crude Oil (CL) hit (HIGH) $110 by end of March?",
      "event_title": "Will Crude Oil (CL) hit__ by end of March?",
      "spike_direction": "down",
      "spike_delta": -0.395,
      "spike_timestamp_before": "2026-02-28T19:30:31+00:00",
      "spike_timestamp_after": "2026-02-28T21:30:57+00:00"
    }
  ]
}