{
  "spike_index": 2,
  "direction": "up",
  "price_before": 0.05,
  "price_after": 0.3,
  "delta": 0.25,
  "abs_delta": 0.25,
  "timestamp_before": "2026-03-01T03:30:32+00:00",
  "timestamp_after": "2026-03-01T20:00:30+00:00",
  "num_articles_ok": 5,
  "num_articles_failed": 0,
  "articles": [
    {
      "url": "https://thehill.com/policy/defense/5760747-trump-iran-regime-change/",
      "file": "2322b3ae8367.txt",
      "title": "Five takeaways as Trump wages war on Iran",
      "published_date": "2026-02-28T00:00:00.000Z",
      "author": null,
      "text_length": 9574,
      "status": "ok",
      "num_tokens": 1937
    },
    {
      "url": "https://www.iranintl.com/en/202603010908",
      "file": "1030cddc8839.txt",
      "title": "Retired US general says Persian Gulf states preparing offensive operations against Iran | Iran International",
      "published_date": "2026-03-01T00:00:00.000Z",
      "author": null,
      "text_length": 87,
      "status": "ok",
      "num_tokens": 13
    },
    {
      "url": "https://www.foxnews.com/media/keane-warns-iran-strike-becoming-regional-war-says-three-gulf-states-preparing-combat.print",
      "file": "0f0ea82a5a50.txt",
      "title": "Keane warns Iran strike becoming \u2018regional war,' says three Gulf states preparing for combat",
      "published_date": "2026-03-01T00:00:00.000Z",
      "author": null,
      "text_length": 2635,
      "status": "ok",
      "num_tokens": 539
    },
    {
      "url": "https://amp.dw.com/en/iran-war-saudi-arabia-united-arab-emeriates-bahrain-qatar-involvement/a-76175593",
      "file": "48994f18b939.txt",
      "title": "Will Gulf states enter the Iran war?",
      "published_date": "2026-03-01T00:00:00.000Z",
      "author": "Cathrin Schaer  Author for the Middle East desk.",
      "text_length": 6723,
      "status": "ok",
      "num_tokens": 1314
    },
    {
      "url": "https://www.nbcnews.com/world/iran/us-israel-attacks-iran-protests-nuclear-talks-rcna253784",
      "file": "bf8079ad4c4c.txt",
      "title": "U.S. and Israel attack Iran as Trump urges Iranians to 'take over' the government",
      "published_date": "2026-02-28T00:00:00.000Z",
      "author": null,
      "text_length": 11685,
      "status": "ok",
      "num_tokens": 2307
    }
  ],
  "total_tokens": 6110
}