{
  "spike_index": 5,
  "direction": "up",
  "price_before": 0.0915,
  "price_after": 0.2595,
  "delta": 0.168,
  "abs_delta": 0.168,
  "timestamp_before": "2026-03-13T14:30:26+00:00",
  "timestamp_after": "2026-03-13T23:30:28+00:00",
  "num_articles_ok": 5,
  "num_articles_failed": 0,
  "articles": [
    {
      "url": "https://thetimes.com/world/middle-east/article/iran-us-war-ground-operation-isfahan-nuclear-facility-bp8rbhs2n",
      "file": "83bbc461ac5e.txt",
      "title": "Elite US troops may launch \u2018snatch raid\u2019 on Iran\u2019s nuclear stockpile",
      "published_date": "2026-03-11T00:00:00.000Z",
      "author": "Larisa Brown, Defence Editor",
      "text_length": 4745,
      "status": "ok",
      "num_tokens": 996
    },
    {
      "url": "https://www.aljazeera.com/amp/news/2026/3/11/could-the-us-deploy-troops-to-iran-and-how-could-that-play-out",
      "file": "dc5368723c54.txt",
      "title": "Could the US deploy troops to Iran, and how could that play out? | US-Israel war on Iran News | Al Jazeera",
      "published_date": "2026-03-11T00:00:00.000Z",
      "author": "Shola Lawal",
      "text_length": 10736,
      "status": "ok",
      "num_tokens": 2155
    },
    {
      "url": "https://timesofindia.indiatimes.com/defence/international/could-us-forces-raid-irans-nuclear-sites-what-are-its-options-operation-epic-fury-trump-israel/articleshow/129503359.cms",
      "file": "66059861799f.txt",
      "title": "Could US forces raid Iran\u2019s nuclear sites? What are its options - The Times of India",
      "published_date": "2026-03-12T00:00:00.000Z",
      "author": "TOI World Desk  / TIMESOFINDIA.COM /   Mar 12, 2026, 18:23 IST",
      "text_length": 7047,
      "status": "ok",
      "num_tokens": 1241
    },
    {
      "url": "https://www.abc.net.au/news/2026-03-12/donald-trump-and-iran-oil-could-involve-kharg-island/106429772",
      "file": "09a58d922f82.txt",
      "title": "Kharg Island could be Iran's weak spot as Washington reportedly considers ground invasion options - ABC News",
      "published_date": "2026-03-11T00:00:00.000Z",
      "author": null,
      "text_length": 8130,
      "status": "ok",
      "num_tokens": 1617
    },
    {
      "url": "https://www.pbs.org/newshour/world/tehran-claims-the-u-s-attacked-it-from-the-uae-as-iran-war-enters-its-third-week",
      "file": "80d3599b82fb.txt",
      "title": "Tehran claims the U.S. attacked it from the UAE as Iran war enters its third week | PBS News",
      "published_date": "2026-03-14T00:00:00.000Z",
      "author": null,
      "text_length": 6154,
      "status": "ok",
      "num_tokens": 1316
    }
  ],
  "total_tokens": 7325
}