{
  "spike_index": 18,
  "direction": "down",
  "price_before": 0.64,
  "price_after": 0.475,
  "delta": -0.16500000000000004,
  "abs_delta": 0.16500000000000004,
  "timestamp_before": "2026-03-02T04:00:34+00:00",
  "timestamp_after": "2026-03-02T13:00:36+00:00",
  "num_articles_ok": 5,
  "num_articles_failed": 0,
  "articles": [
    {
      "url": "https://www.barrons.com/articles/aes-stock-take-private-acquisition-3d7d72be?gaa_at=eafs&gaa_n=AWEtsqc7bUFgAX81ZSOFuURCkz_yUzlMG4MG2RW-kKFhUqdRaR_8C6roAB6s&gaa_sig=LJ-2Ltrb4J_5AGicj74ba3JjdD9No_ouxTM3H43PDb2zMTb4OhYlYYmoHcbknnWujjI6zSDouTFO2Qwp96V38g%3D%3D&gaa_ts=69a5ca93",
      "file": "83888f519f45.txt",
      "title": "AES to Be Taken Private in $33 Billion Deal. Why It\u2019s the S&P 500\u2019s Worst Stock Today. - Barron's",
      "published_date": "2026-03-02T00:00:00.000Z",
      "author": "Nate Wolf",
      "text_length": 192,
      "status": "ok",
      "num_tokens": 33
    },
    {
      "url": "https://origin.www.bloomberg.com/news/articles/2026-03-02/bavarian-nordic-ceo-steps-down-after-failed-3-billion-deal?srnd=undefined",
      "file": "9f247bf8b70c.txt",
      "title": "Bavarian Nordic CEO to Leave After Failed $3 Billion Takeover Bid - Bloomberg",
      "published_date": "2026-03-02T00:00:00.000Z",
      "author": "Christian Wienberg",
      "text_length": 406,
      "status": "ok",
      "num_tokens": 87
    },
    {
      "url": "https://markets.ft.com/data/announce/full?dockey=600-202603020630BIZWIRE_USPRX____20260302_BW029271-1",
      "file": "a37e625383f5.txt",
      "title": "Kairos Pharma Announces Signing of Binding Strategic Asset Acquisition of Exclusive Worldwide Rights to CL-273 From OrbiMed and Torrey Pines Investment-Backed Celyn Therapeutics \u2013 Company Announcement - FT.com",
      "published_date": "2026-03-02T00:00:00.000Z",
      "author": null,
      "text_length": 7386,
      "status": "ok",
      "num_tokens": 1450
    },
    {
      "url": "https://markets.ft.com/data/announce/detail?dockey=600-202603021606BIZWIRE_USPRX____20260302_BW126591-1",
      "file": "3be052d609c5.txt",
      "title": "Vitesse Energy Announces Signing of Accretive Acquisition, Fourth Quarter and Full Year 2025 Results, and Issues 2026 Production and Capital Expenditures Guidance \u2013 Company Announcement - FT.com",
      "published_date": "2026-03-02T00:00:00.000Z",
      "author": null,
      "text_length": 28447,
      "status": "ok",
      "num_tokens": 7425
    },
    {
      "url": "https://today.reuters.com/world/asia-pacific/toyota-plans-hike-offer-price-group-firm-tico-extend-deadline-again-2026-03-02/",
      "file": "db68093eb0c6.txt",
      "title": "Toyota bumps offer for supplier to $30 billion, in a victory for activist fund Elliott | Reuters",
      "published_date": "2026-03-02T00:00:00.000Z",
      "author": "Daniel Leussink",
      "text_length": 3850,
      "status": "ok",
      "num_tokens": 780
    }
  ],
  "total_tokens": 9775
}