{
  "hash": "558730189de5",
  "n_appearances": 1,
  "n_distinct_urls": 1,
  "sources": [
    {
      "url": "https://abcnews.go.com/GMA/News/video/us-military-moves-position-iran-strikes-130362395",
      "title": "Video US military moves into position for possible Iran strikes - ABC News",
      "published_date": "2026-02-21T00:00:00.000Z",
      "author": "ABC News",
      "num_tokens": 54,
      "text_length": 261
    }
  ],
  "appearances": [
    {
      "market_id": "1386650",
      "spike_id": 1,
      "market_question": "US strikes Iran by February 21, 2026?",
      "event_title": "US strikes Iran by...?",
      "spike_direction": "down",
      "spike_delta": -0.669,
      "spike_timestamp_before": "2026-02-21T21:30:22+00:00",
      "spike_timestamp_after": "2026-02-22T04:30:17+00:00"
    }
  ]
}