{
  "hash": "e19fe4ca6ace",
  "n_appearances": 2,
  "n_distinct_urls": 1,
  "sources": [
    {
      "url": "https://www.npr.org/2026/02/28/1123499337/iran-israel-ayatollah-ali-khamenei-killed",
      "title": "Iran's Supreme Leader Ayatollah Ali Khamenei killed by Israel at 86 : NPR",
      "published_date": "2026-02-28T00:00:00.000Z",
      "author": null,
      "num_tokens": 2273,
      "text_length": 10174
    }
  ],
  "appearances": [
    {
      "market_id": "1180303",
      "spike_id": 4,
      "market_question": "Khamenei out as Supreme Leader of Iran by February 28?",
      "event_title": "Khamenei out as Supreme Leader of Iran by February 28?",
      "spike_direction": "up",
      "spike_delta": 0.9895,
      "spike_timestamp_before": "2026-02-28T05:30:25+00:00",
      "spike_timestamp_after": "2026-03-01T03:30:27+00:00"
    },
    {
      "market_id": "1180303",
      "spike_id": 5,
      "market_question": "Khamenei out as Supreme Leader of Iran by February 28?",
      "event_title": "Khamenei out as Supreme Leader of Iran by February 28?",
      "spike_direction": "up",
      "spike_delta": 0.935,
      "spike_timestamp_before": "2026-02-28T13:00:26+00:00",
      "spike_timestamp_after": "2026-03-01T09:00:39+00:00"
    }
  ]
}