{
  "spike_index": 15,
  "direction": "up",
  "price_before": 0.485,
  "price_after": 0.635,
  "delta": 0.15000000000000002,
  "abs_delta": 0.15000000000000002,
  "timestamp_before": "2026-03-04T12:30:32+00:00",
  "timestamp_after": "2026-03-05T03:00:24+00:00",
  "num_articles_ok": 5,
  "num_articles_failed": 0,
  "articles": [
    {
      "url": "https://www.newsweek.com/100k-polymarket-winner-wagers-on-us-forces-entering-iran-11633078",
      "file": "a517bdff21c0.txt",
      "title": "$100K Polymarket winner wagers on US forces entering Iran - Newsweek",
      "published_date": "2026-03-06T00:00:00.000Z",
      "author": null,
      "text_length": 4231,
      "status": "ok",
      "num_tokens": 863
    },
    {
      "url": "https://reuters.com/business/aerospace-defense/top-us-general-outlines-initial-timeline-us-military-operation-iran-2026-03-02/",
      "file": "ac7bedb143ff.txt",
      "title": "Top U.S. general outlines initial timeline of U.S. military operation in Iran | Reuters",
      "published_date": "2026-03-02T00:00:00.000Z",
      "author": null,
      "text_length": 2525,
      "status": "ok",
      "num_tokens": 576
    },
    {
      "url": "https://thehill.com/policy/international/5771098-donald-trump-us-iran-deal-surrender-nuclear/",
      "file": "b868e90ef2c1.txt",
      "title": "Donald Trump urges Iran's surrender, vows to restore Middle East nation",
      "published_date": "2026-03-06T00:00:00.000Z",
      "author": null,
      "text_length": 5059,
      "status": "ok",
      "num_tokens": 1024
    },
    {
      "url": "https://www.nbcnews.com/politics/national-security/russia-providing-intelligence-iran-location-us-forces-sources-say-rcna262115",
      "file": "39169345c400.txt",
      "title": "Russia is providing intelligence to Iran on the location of U.S. forces, sources say",
      "published_date": "2026-03-06T00:00:00.000Z",
      "author": null,
      "text_length": 4716,
      "status": "ok",
      "num_tokens": 968
    },
    {
      "url": "https://www.newsweek.com/trump-admin-gives-update-on-americans-evacuated-from-middle-east-11627892",
      "file": "fef6fc9ab530.txt",
      "title": "Middle East War: Trump Admin Gives Update on 20,000 Americans Evacuated - Newsweek",
      "published_date": "2026-03-05T00:00:00.000Z",
      "author": null,
      "text_length": 7756,
      "status": "ok",
      "num_tokens": 1534
    }
  ],
  "total_tokens": 4965
}