{
  "spike_index": 4,
  "direction": "down",
  "price_before": 0.435,
  "price_after": 0.245,
  "delta": -0.19,
  "abs_delta": 0.19,
  "timestamp_before": "2026-03-04T23:00:28+00:00",
  "timestamp_after": "2026-03-05T21:30:25+00:00",
  "num_articles_ok": 5,
  "num_articles_failed": 0,
  "articles": [
    {
      "url": "https://amp.dw.com/en/iran-war-what-role-will-yemens-houthi-group-play/a-76216075",
      "file": "46a58ff98a23.txt",
      "title": "Iran war: What role will Yemen's Houthi group play?",
      "published_date": "2026-03-05T00:00:00.000Z",
      "author": "Kersten Knipp  Political editor with a focus on the Middle East",
      "text_length": 5136,
      "status": "ok",
      "num_tokens": 1062
    },
    {
      "url": "https://foreignpolicy.com/2026/03/02/iran-war-hezbollah-lebabon-houthis-yemen-iraq-proxies/",
      "file": "3fa33cf2a706.txt",
      "title": "Iran\u2019s Proxies in Lebanon, Iraq, and Yemen Are Out for Themselves for Now",
      "published_date": "2026-03-02T00:00:00.000Z",
      "author": "Anchal Vohra",
      "text_length": 8901,
      "status": "ok",
      "num_tokens": 1797
    },
    {
      "url": "https://hoffman.foreignpolicy.com/2026/03/02/iran-war-hezbollah-lebabon-houthis-yemen-iraq-proxies/?tpcc=recirc_right_rail051524",
      "file": "106afb6f667a.txt",
      "title": "Iran\u2019s Proxies in Lebanon, Iraq, and Yemen Are Out for Themselves for Now",
      "published_date": "2026-03-02T00:00:00.000Z",
      "author": "Anchal Vohra",
      "text_length": 8596,
      "status": "ok",
      "num_tokens": 1747
    },
    {
      "url": "https://haaretz.com/israel-news/israel-security/2026-03-05/ty-article/.premium/iran-has-fired-at-least-six-cluster-missiles-at-israel-since-the-war-began/0000019c-b94e-db5a-a99f-b94ff6f20000",
      "file": "4eae37dfa86f.txt",
      "title": "Iran Has Fired at Least Six Cluster Missiles at Israel Since the War Began - Israel Security",
      "published_date": "2026-03-04T00:00:00.000Z",
      "author": "Josh Breiner",
      "text_length": 344,
      "status": "ok",
      "num_tokens": 71
    },
    {
      "url": "https://www.reuters.com/investigations/iran-spent-years-fostering-proxies-iraq-now-many-arent-eager-join-war-2026-03-06/",
      "file": "cc63c62b2bd3.txt",
      "title": "Iran spent years fostering proxies in Iraq. Now, many aren\u2019t eager to join the war | Reuters",
      "published_date": "2026-03-06T00:00:00.000Z",
      "author": "John Davison",
      "text_length": 20992,
      "status": "ok",
      "num_tokens": 4400
    }
  ],
  "total_tokens": 9077
}