{
  "hash": "3629fa69af2b",
  "n_appearances": 4,
  "n_distinct_urls": 1,
  "sources": [
    {
      "url": "https://www.cnbc.com/2026/03/02/iran-israel-us-conflict-oil-jumps-trump-netanyahu-what-is-next.html",
      "title": "Iran conflict: Where things stand, global responses — and what comes next",
      "published_date": "2026-03-01T00:00:00.000Z",
      "author": "Anniek Bao",
      "num_tokens": 1529,
      "text_length": 7268
    }
  ],
  "appearances": [
    {
      "market_id": "1466012",
      "spike_id": 1,
      "market_question": "US x Iran ceasefire by March 2?",
      "event_title": "US x Iran ceasefire by...?",
      "spike_direction": "up",
      "spike_delta": 0.156,
      "spike_timestamp_before": "2026-02-28T15:00:24+00:00",
      "spike_timestamp_after": "2026-02-28T21:00:26+00:00"
    },
    {
      "market_id": "663583",
      "spike_id": 1,
      "market_question": "Will the Iranian regime fall before 2027?",
      "event_title": "Will the Iranian regime fall before 2027?",
      "spike_direction": "up",
      "spike_delta": 0.16000000000000003,
      "spike_timestamp_before": "2026-02-27T07:30:40+00:00",
      "spike_timestamp_after": "2026-02-28T07:00:40+00:00"
    },
    {
      "market_id": "663583",
      "spike_id": 2,
      "market_question": "Will the Iranian regime fall before 2027?",
      "event_title": "Will the Iranian regime fall before 2027?",
      "spike_direction": "up",
      "spike_delta": 0.21499999999999997,
      "spike_timestamp_before": "2026-02-27T10:00:37+00:00",
      "spike_timestamp_after": "2026-02-28T09:30:39+00:00"
    },
    {
      "market_id": "663583",
      "spike_id": 3,
      "market_question": "Will the Iranian regime fall before 2027?",
      "event_title": "Will the Iranian regime fall before 2027?",
      "spike_direction": "up",
      "spike_delta": 0.25,
      "spike_timestamp_before": "2026-02-27T23:00:46+00:00",
      "spike_timestamp_after": "2026-02-28T22:30:36+00:00"
    }
  ]
}